{
  "id": 160517,
  "nome": "Paulo Folletto",
  "partido": "PSB",
  "uf": "ES",
  "foto_url": "https://www.camara.leg.br/internet/deputado/bandep/160517.jpg",
  "score": 28.4,
  "rank": 212,
  "proposicoes": [],
  "discursos": [],
  "orgaos": [
    {
      "nome": "Comissão Especial destinada a acompanhar as ações de prevenção e combate ao câncer, ao acidente vascular cerebral (AVC) e às doenças do coração.",
      "sigla": "CECANCER",
      "cargo": "Suplente",
      "desde": "2024-02-07T00:00"
    },
    {
      "nome": "Mesa Diretora da Câmara dos Deputados",
      "sigla": "MESA",
      "cargo": "2º Suplente de Secretário",
      "desde": "2025-02-01T00:00"
    },
    {
      "nome": "Mesa Diretora da Câmara dos Deputados",
      "sigla": "MESA",
      "cargo": "Suplente",
      "desde": "2025-02-01T00:00"
    },
    {
      "nome": "Comissão Especial destinada a proferir parecer ao Projeto de Lei nº 3080, de 2020, do Senhor Alexandre Frota, que \"Institui a política pública nacional para garantia, proteção e ampliação dos direitos das pessoas com Transtorno do Espectro Autismo, e dá outras providências\", e apensados",
      "sigla": "PL308020",
      "cargo": "Titular",
      "desde": "2025-10-20T00:00"
    },
    {
      "nome": "Comissão de Saúde",
      "sigla": "CSAUDE",
      "cargo": "Titular",
      "desde": "2026-02-03T00:00"
    },
    {
      "nome": "Comissão de Administração e Serviço Público",
      "sigla": "CASP",
      "cargo": "Suplente",
      "desde": "2026-02-04T00:00"
    }
  ],
  "url_votacoes": "https://www.camara.leg.br/deputados/160517/votacoes-nominais-plenario/2026"
}