{
  "id": 160666,
  "nome": "Félix Mendonça Júnior",
  "partido": "PDT",
  "uf": "BA",
  "foto_url": "https://www.camara.leg.br/internet/deputado/bandep/160666.jpg",
  "score": 31.48,
  "rank": 76,
  "proposicoes": [
    {
      "id": 2638932,
      "tipo": "PL",
      "numero": 3641,
      "ano": 2026,
      "ementa": "Dispõe sobre a criação da Universidade Federal do Noroeste da Bahia, com sede no Município de Irecê.",
      "data": "2026-07-10T15:16",
      "url": "https://www.camara.leg.br/proposicoesWeb/fichadetramitacao?idProposicao=2638932"
    }
  ],
  "discursos": [],
  "orgaos": [
    {
      "nome": "Bancada Negra da Câmara dos Deputados, criada pela Resolução n. 6, de 2023, que acresceu ao Regimento Interno da Câmara dos Deputados o Capítulo VI, do Título I, com os artigos 13-A e 13-B",
      "sigla": "BANEGRA",
      "cargo": "Titular",
      "desde": "2023-11-02T00:00"
    },
    {
      "nome": "Centro de Estudos e Debates Estratégicos",
      "sigla": "CEDES",
      "cargo": "Titular",
      "desde": "2024-02-07T00:00"
    },
    {
      "nome": "Secretaria de Relações Internacionais",
      "sigla": "SRI",
      "cargo": "Secretário de Relações Internacionais",
      "desde": "2025-04-09T00:00"
    },
    {
      "nome": "Secretaria de Relações Internacionais",
      "sigla": "SRI",
      "cargo": "Titular",
      "desde": "2025-04-09T00:00"
    },
    {
      "nome": "Comissão de Agricultura, Pecuária, Abastecimento e Desenvolvimento Rural",
      "sigla": "CAPADR",
      "cargo": "Suplente",
      "desde": "2026-02-04T00:00"
    },
    {
      "nome": "Comissão de Constituição e Justiça e de Cidadania",
      "sigla": "CCJC",
      "cargo": "Titular",
      "desde": "2026-02-09T00:00"
    },
    {
      "nome": "Comissão Mista de Planos, Orçamentos Públicos e Fiscalização",
      "sigla": "CMO",
      "cargo": "Suplente",
      "desde": "2026-06-15T00:00"
    }
  ],
  "url_votacoes": "https://www.camara.leg.br/deputados/160666/votacoes-nominais-plenario/2026"
}