{
  "id": 204362,
  "nome": "Ricardo Guidi",
  "partido": "PL",
  "uf": "SC",
  "foto_url": "https://www.camara.leg.br/internet/deputado/bandep/204362.jpg",
  "score": 28.86,
  "rank": 312,
  "proposicoes": [],
  "discursos": [],
  "orgaos": [
    {
      "nome": "Comissão de Minas e Energia",
      "sigla": "CME",
      "cargo": "Titular",
      "desde": "2026-02-03T00:00"
    },
    {
      "nome": "Comissão de Defesa dos Direitos das Pessoas com Deficiência",
      "sigla": "CPD",
      "cargo": "Suplente",
      "desde": "2026-02-03T00:00"
    },
    {
      "nome": "Comissão de Meio Ambiente e Desenvolvimento Sustentável",
      "sigla": "CMADS",
      "cargo": "Suplente",
      "desde": "2026-03-03T00:00"
    }
  ],
  "url_votacoes": "https://www.camara.leg.br/deputados/204362/votacoes-nominais-plenario/2026"
}