{
  "id": 204419,
  "nome": "Glaustin da Fokus",
  "partido": "PODE",
  "uf": "GO",
  "foto_url": "https://www.camara.leg.br/internet/deputado/bandep/204419.jpg",
  "score": 12.61,
  "rank": 485,
  "proposicoes": [
    {
      "id": 2623604,
      "tipo": "PEC",
      "numero": 9,
      "ano": 2026,
      "ementa": "Altera o art. 228 da Constituição Federal, para reduzir a idade mínima de imputabilidade penal, nas condições que estabelece.",
      "data": "2026-05-12T11:28",
      "url": "https://www.camara.leg.br/proposicoesWeb/fichadetramitacao?idProposicao=2623604"
    },
    {
      "id": 2624861,
      "tipo": "EMC",
      "numero": 1,
      "ano": 0,
      "ementa": "Altera o Art. 7º inciso XIII da Constituição Federal, reduzindo a jornada de trabalho a 36 horas semanais em 10 anos.",
      "data": "2026-05-14T13:51",
      "url": "https://www.camara.leg.br/proposicoesWeb/fichadetramitacao?idProposicao=2624861"
    },
    {
      "id": 2624863,
      "tipo": "EMC",
      "numero": 2,
      "ano": 0,
      "ementa": "Altera o Art. 7º inciso XII da constituição Federal, reduzindo a jornada de trabalho a 36 horas semanais em 10 anos.",
      "data": "2026-05-14T14:15",
      "url": "https://www.camara.leg.br/proposicoesWeb/fichadetramitacao?idProposicao=2624863"
    }
  ],
  "discursos": [],
  "orgaos": [
    {
      "nome": "Comissão Especial destinada a proferir parecer ao Projeto de Lei Complementar nº 234, de 2024, do Sr. Felipe Carreras, que \"dispõe sobre incentivos e benefícios para fomentar as atividades de caráter desportivo e dá outras providências\"",
      "sigla": "PLP23424",
      "cargo": "Suplente",
      "desde": "2025-12-03T00:00"
    },
    {
      "nome": "Comissão de Direitos Humanos, Minorias e Igualdade Racial",
      "sigla": "CDHMIR",
      "cargo": "Titular",
      "desde": "2026-02-25T00:00"
    },
    {
      "nome": "Comissão Especial destinada a proferir parecer à Proposta de Emenda à Constituição nº 221, de 2019, do Senhor Reginaldo Lopes, que \"altera o Art. 7º inciso XII da constituição Federal, reduzindo a jornada de trabalho a 36 horas semanais em 10 anos\", e apensada",
      "sigla": "PEC22119",
      "cargo": "Titular",
      "desde": "2026-04-29T00:00"
    }
  ],
  "url_votacoes": "https://www.camara.leg.br/deputados/204419/votacoes-nominais-plenario/2026"
}