{
  "id": 204410,
  "nome": "Luisa Canziani",
  "partido": "UNIÃO",
  "uf": "PR",
  "foto_url": "https://www.camara.leg.br/internet/deputado/bandep/204410.jpg",
  "score": 16.45,
  "rank": 449,
  "proposicoes": [],
  "discursos": [],
  "orgaos": [
    {
      "nome": "Secretaria da Mulher",
      "sigla": "SEMULHER",
      "cargo": "Titular",
      "desde": "2023-05-04T00:00"
    },
    {
      "nome": "Comissão Especial destinada a proferir parecer ao Projeto de Lei nº 2338, de 2023, do Senado Federal, que \"dispõe sobre o desenvolvimento, o fomento e o uso ético e responsável da inteligência artificial com base na centralidade da pessoa humana\"",
      "sigla": "PL233823",
      "cargo": "Presidente",
      "desde": "2025-05-20T00:00"
    },
    {
      "nome": "Comissão Especial destinada a proferir parecer à Proposta de Emenda à Constituição nº 34, de 2024, da Senhora Laura Carneiro e outros, que \"inclui a primeira infância como beneficiária de direitos e garantias, no texto constitucional\"",
      "sigla": "PEC03424",
      "cargo": "Suplente",
      "desde": "2025-10-02T00:00"
    },
    {
      "nome": "Comissão do Esporte",
      "sigla": "CESPO",
      "cargo": "Suplente",
      "desde": "2026-02-03T00:00"
    },
    {
      "nome": "Comissão de Ciência, Tecnologia e Inovação",
      "sigla": "CCTI",
      "cargo": "2º Vice-Presidente",
      "desde": "2026-05-13T00:00"
    }
  ],
  "url_votacoes": "https://www.camara.leg.br/deputados/204410/votacoes-nominais-plenario/2026"
}