{
  "id": 220553,
  "nome": "Denise Pessôa",
  "partido": "PT",
  "uf": "RS",
  "foto_url": "https://www.camara.leg.br/internet/deputado/bandep/220553.jpg",
  "score": 38.27,
  "rank": 27,
  "proposicoes": [
    {
      "id": 2608871,
      "tipo": "PL",
      "numero": 1157,
      "ano": 2026,
      "ementa": "Altera a Lei nº 7.716, de 8 de janeiro de 1989, para instituir mecanismos de proteção e assistência integral à vítima de crimes resultantes de discriminação ou preconceito de raça, cor, etnia, religião ou procedência nacional, com foco no atendimento especializado e na não revitimização.",
      "data": "2026-03-13T13:32",
      "url": "https://www.camara.leg.br/proposicoesWeb/fichadetramitacao?idProposicao=2608871"
    },
    {
      "id": 2608964,
      "tipo": "SBT",
      "numero": 1,
      "ano": 0,
      "ementa": "Confere ao Município de Flores da Cunha, no Estado do Rio Grande do Sul, o título de Capital Nacional da Vindima e institui o mês de janeiro como o período para a realização do evento de Abertura Nacional da Colheita da Uva, nesse mesmo município.",
      "data": "2026-03-16T11:28",
      "url": "https://www.camara.leg.br/proposicoesWeb/fichadetramitacao?idProposicao=2608964"
    },
    {
      "id": 2609535,
      "tipo": "EMP",
      "numero": 2,
      "ano": 0,
      "ementa": "Emenda de Plenário para instituir o Programa Nacional de Tarifa Zero para o Transporte Urbano.",
      "data": "2026-03-17T16:52",
      "url": "https://www.camara.leg.br/proposicoesWeb/fichadetramitacao?idProposicao=2609535"
    },
    {
      "id": 2611435,
      "tipo": "SBT",
      "numero": 1,
      "ano": 0,
      "ementa": "Institui a Política Nacional para as Comissões de Apoio à Cinematografia (film commissions).",
      "data": "2026-03-24T12:49",
      "url": "https://www.camara.leg.br/proposicoesWeb/fichadetramitacao?idProposicao=2611435"
    },
    {
      "id": 2612382,
      "tipo": "SBT",
      "numero": 1,
      "ano": 0,
      "ementa": "Institui a criação de espaços de acolhimento para mulheres em eventos culturais, festivais de música e casas de shows.",
      "data": "2026-03-26T14:23",
      "url": "https://www.camara.leg.br/proposicoesWeb/fichadetramitacao?idProposicao=2612382"
    },
    {
      "id": 2612399,
      "tipo": "PL",
      "numero": 1440,
      "ano": 2026,
      "ementa": "Altera a Lei nº 14.192, de 4 de agosto de 2021, para dispor sobre o combate à violência política de gênero e raça, inclusive em meios digitais, e dá outras providências.",
      "data": "2026-03-26T14:16",
      "url": "https://www.camara.leg.br/proposicoesWeb/fichadetramitacao?idProposicao=2612399"
    },
    {
      "id": 2612861,
      "tipo": "PL",
      "numero": 1537,
      "ano": 2026,
      "ementa": "Dispõe sobre o reconhecimento, valorização, proteção previdenciária e salvaguarda do ofício, saberes e práticas das parteiras tradicionais como atividade essencial à reprodução social, cultural e comunitária, e dá outras providências, nos termos da Constituição Federal.",
      "data": "2026-03-30T20:34",
      "url": "https://www.camara.leg.br/proposicoesWeb/fichadetramitacao?idProposicao=2612861"
    },
    {
      "id": 2613302,
      "tipo": "PL",
      "numero": 1583,
      "ano": 2026,
      "ementa": "Altera a Lei nº 8.742, de 7 de dezembro de 1993 – Lei Orgânica da Assistência Social (Loas), para instituir o Benefício Assistencial de Amparo à Família do Beneficiário Falecido, destinado aos cuidadores e ao conjunto de dependentes por óbito do titular de benefício de prestação continuada (BPC), e a Lei nº 14.601, de 19 de junho de 2023, para dispor sobre a composição do cálculo da renda familiar per capita mensal do Programa Bolsa Família.",
      "data": "2026-04-01T17:33",
      "url": "https://www.camara.leg.br/proposicoesWeb/fichadetramitacao?idProposicao=2613302"
    },
    {
      "id": 2613879,
      "tipo": "PL",
      "numero": 1649,
      "ano": 2026,
      "ementa": "Altera a Lei nº 13.445, de 24 de maio de 2017 (Lei de Migração), dispõe sobre o estatuto do imigrante sazonal.",
      "data": "2026-04-07T16:19",
      "url": "https://www.camara.leg.br/proposicoesWeb/fichadetramitacao?idProposicao=2613879"
    },
    {
      "id": 2615287,
      "tipo": "PL",
      "numero": 1754,
      "ano": 2026,
      "ementa": "Institui a TerraBras, empresa pública destinada à defesa da soberania nacional e ao aproveitamento dos minerais críticos ou estratégicos; estabelece o regime de partilha da produção mineral; altera o Decreto-Lei nº 227, de 28 de fevereiro de 1967, a Lei nº 8.970, de 28 de dezembro de 1994, e a Lei nº 13.575, de 26 de dezembro de 2017; e dá outras providências.",
      "data": "2026-04-10T14:32",
      "url": "https://www.camara.leg.br/proposicoesWeb/fichadetramitacao?idProposicao=2615287"
    }
  ],
  "discursos": [],
  "orgaos": [
    {
      "nome": "Secretaria da Mulher",
      "sigla": "SEMULHER",
      "cargo": "Titular",
      "desde": "2023-05-04T00:00"
    },
    {
      "nome": "Bancada Negra da Câmara dos Deputados, criada pela Resolução n. 6, de 2023, que acresceu ao Regimento Interno da Câmara dos Deputados o Capítulo VI, do Título I, com os artigos 13-A e 13-B",
      "sigla": "BANEGRA",
      "cargo": "Titular",
      "desde": "2023-11-02T00:00"
    },
    {
      "nome": "Comissão Externa destinada a apurar e acompanhar os danos causados pelas enchentes de 2023 e 2024, que atingiram o estado do Rio Grande do Sul",
      "sigla": "CEXCIRS",
      "cargo": "Titular",
      "desde": "2023-11-28T00:00"
    },
    {
      "nome": "Comissão Especial destinada a proferir parecer à Proposta de Emenda à Constituição nº 5, de 2023, do Sr. Marcelo Crivella e outros, que \"acrescenta § 4º-A ao art. 150 da Constituição Federal, para dispor sobre a imunidade tributária de que tratam as suas alíneas “b” e “c” do inciso VI\"",
      "sigla": "PEC00523",
      "cargo": "Titular",
      "desde": "2024-02-07T00:00"
    },
    {
      "nome": "Comissão Especial para estudo das razões do aumento de denúncias de violência obstétrica e a alta taxa de morte materna no Brasil",
      "sigla": "CEOBSTET",
      "cargo": "Titular",
      "desde": "2024-02-07T00:00"
    },
    {
      "nome": "Comissão Especial destinada a estudar e analisar formas de prevenção e auxílio a desastres e calamidades naturais que vêm assolando o Território Nacional",
      "sigla": "CEDESNAT",
      "cargo": "Titular",
      "desde": "2024-05-14T00:00"
    },
    {
      "nome": "Comissão Especial destinada a proferir parecer ao Projeto de Lei nº 2338, de 2023, do Senado Federal, que \"dispõe sobre o desenvolvimento, o fomento e o uso ético e responsável da inteligência artificial com base na centralidade da pessoa humana\"",
      "sigla": "PL233823",
      "cargo": "Suplente",
      "desde": "2025-05-06T00:00"
    },
    {
      "nome": "Comissão Externa destinada a acompanhar os graves casos de feminicídios ocorridos no Estado do Rio Grande do Sul",
      "sigla": "CEXRSFEM",
      "cargo": "Subcoordenador",
      "desde": "2025-05-28T00:00"
    },
    {
      "nome": "Comissão Externa destinada a acompanhar os graves casos de feminicídios ocorridos no Estado do Rio Grande do Sul",
      "sigla": "CEXRSFEM",
      "cargo": "Titular",
      "desde": "2025-05-28T00:00"
    },
    {
      "nome": "Comissão Especial destinada a proferir parecer à Proposta de Emenda à Constituição nº 27, de 2024, do Senhor Damião Feliciano e outros, que \"altera a Constituição Federal para acrescentar o Capítulo IX - Da Promoção Da Igualdade Racial, que institui o Fundo Nacional de Reparação Econômica e de Promoção da Igualdade Racial (FNREPIR) com o objetivo de promover a igualdade de oportunidades e a inclusão social dos brasileiros pretos e pardos, e dá outras providências\"",
      "sigla": "PEC02724",
      "cargo": "Suplente",
      "desde": "2025-09-10T00:00"
    },
    {
      "nome": "Comissão Especial destinada a proferir parecer ao Projeto de Lei nº 3080, de 2020, do Senhor Alexandre Frota, que \"Institui a política pública nacional para garantia, proteção e ampliação dos direitos das pessoas com Transtorno do Espectro Autismo, e dá outras providências\", e apensados",
      "sigla": "PL308020",
      "cargo": "Suplente",
      "desde": "2025-10-20T00:00"
    },
    {
      "nome": "Comissão de Viação e Transportes",
      "sigla": "CVT",
      "cargo": "Titular",
      "desde": "2026-02-03T00:00"
    },
    {
      "nome": "Comissão de Administração e Serviço Público",
      "sigla": "CASP",
      "cargo": "Suplente",
      "desde": "2026-02-04T00:00"
    },
    {
      "nome": "Comissão de Desenvolvimento Urbano",
      "sigla": "CDU",
      "cargo": "Suplente",
      "desde": "2026-02-04T00:00"
    },
    {
      "nome": "Comissão de Cultura",
      "sigla": "CCULT",
      "cargo": "2º Vice-Presidente",
      "desde": "2026-03-04T00:00"
    }
  ],
  "url_votacoes": "https://www.camara.leg.br/deputados/220553/votacoes-nominais-plenario/2026"
}