{
  "id": 220556,
  "nome": "Ana Paula Lima",
  "partido": "PT",
  "uf": "SC",
  "foto_url": "https://www.camara.leg.br/internet/deputado/bandep/220556.jpg",
  "score": 34.9,
  "rank": 54,
  "proposicoes": [
    {
      "id": 2616663,
      "tipo": "PL",
      "numero": 1853,
      "ano": 2026,
      "ementa": "Autoriza a União a instituir empresa estatal, ou subsidiária de sociedade de economia mista federal, para atuar na distribuição de combustíveis, biocombustíveis e gás liquefeito de petróleo (GLP), autoriza a recomposição da presença pública em ativos estratégicos do abastecimento nacional, e estabelece diretrizes para a soberania energética, a segurança do abastecimento, a modicidade de preços e a defesa do consumidor.",
      "data": "2026-04-15T15:34",
      "url": "https://www.camara.leg.br/proposicoesWeb/fichadetramitacao?idProposicao=2616663"
    },
    {
      "id": 2619347,
      "tipo": "SBT",
      "numero": 1,
      "ano": 0,
      "ementa": "Institui o serviço de telemedicina para gestantes em áreas rurais e de difícil acesso e dá outras providências.",
      "data": "2026-04-28T18:17",
      "url": "https://www.camara.leg.br/proposicoesWeb/fichadetramitacao?idProposicao=2619347"
    },
    {
      "id": 2619830,
      "tipo": "SBT",
      "numero": 3,
      "ano": 0,
      "ementa": "",
      "data": "2026-04-29T11:50",
      "url": "https://www.camara.leg.br/proposicoesWeb/fichadetramitacao?idProposicao=2619830"
    },
    {
      "id": 2620149,
      "tipo": "PL",
      "numero": 2096,
      "ano": 2026,
      "ementa": "Altera a Lei n.º 10.048, de 8 de novembro de 2000, para incluir crianças e adolescentes em tratamento oncológico entre os beneficiários do atendimento prioritário, e a Lei n.º 11.930, de 22 de abril de 2009, para prever ações de conscientização sobre o câncer infantojuvenil durante a Semana de Mobilização Nacional para Doação de Medula Óssea – Lei Biel.",
      "data": "2026-04-29T19:26",
      "url": "https://www.camara.leg.br/proposicoesWeb/fichadetramitacao?idProposicao=2620149"
    },
    {
      "id": 2620152,
      "tipo": "PL",
      "numero": 2097,
      "ano": 2026,
      "ementa": "Dispõe sobre a regulação do uso de redes sociais por integrantes das forças de segurança pública, e dá outras providências.",
      "data": "2026-04-29T19:39",
      "url": "https://www.camara.leg.br/proposicoesWeb/fichadetramitacao?idProposicao=2620152"
    },
    {
      "id": 2620197,
      "tipo": "PL",
      "numero": 2101,
      "ano": 2026,
      "ementa": "Dispõe sobre diretrizes para a prevenção, o diagnóstico e o tratamento da Paracoccidioidomicose no âmbito do Sistema Único de Saúde (SUS).",
      "data": "2026-04-29T21:11",
      "url": "https://www.camara.leg.br/proposicoesWeb/fichadetramitacao?idProposicao=2620197"
    },
    {
      "id": 2620199,
      "tipo": "PL",
      "numero": 2102,
      "ano": 2026,
      "ementa": "Dispõe sobre o direito ao Plano de Parto e estabelece diretrizes para sua observância na assistência obstétrica nos estabelecimentos de saúde públicos e privados.",
      "data": "2026-04-29T21:25",
      "url": "https://www.camara.leg.br/proposicoesWeb/fichadetramitacao?idProposicao=2620199"
    },
    {
      "id": 2620934,
      "tipo": "SBT",
      "numero": 2,
      "ano": 0,
      "ementa": "Dispõe sobre a regulamentação da profissão de Terapeuta Floral e dá outras providências.",
      "data": "2026-05-04T19:46",
      "url": "https://www.camara.leg.br/proposicoesWeb/fichadetramitacao?idProposicao=2620934"
    },
    {
      "id": 2621094,
      "tipo": "SBT",
      "numero": 2,
      "ano": 0,
      "ementa": "Dispõe sobre a isenção de tributos, tarifas e despesas para pessoas diagnosticadas com neoplasia maligna, desde o diagnóstico até a alta ou cura clínica, e dá outras providências.",
      "data": "2026-05-05T11:18",
      "url": "https://www.camara.leg.br/proposicoesWeb/fichadetramitacao?idProposicao=2621094"
    },
    {
      "id": 2622301,
      "tipo": "PL",
      "numero": 2230,
      "ano": 2026,
      "ementa": "Altera a Lei n.º 11.340, de 7 de agosto de 2006 (Lei Maria da Penha), para instituir o Programa de Prevenção à Violência de Gênero Extrafamiliar – PREVIGEN e ampliar o âmbito de proteção às mulheres em situação de violência de gênero; altera o Decreto-Lei n.º 2.848, de 7 de dezembro de 1940 (Código Penal), para estabelecer causas de aumento de pena em crimes praticados contra a mulher em razão da condição de sexo feminino; e estabelece diretrizes para políticas de prevenção.",
      "data": "2026-05-06T17:00",
      "url": "https://www.camara.leg.br/proposicoesWeb/fichadetramitacao?idProposicao=2622301"
    },
    {
      "id": 2622855,
      "tipo": "SBT",
      "numero": 3,
      "ano": 0,
      "ementa": "Institui objetivos e diretrizes relacionados com a inserção de Enfermeiros, Técnicos e Auxiliares de Enfermagem recém-formados no mercado de trabalho em todo país.",
      "data": "2026-05-06T17:06",
      "url": "https://www.camara.leg.br/proposicoesWeb/fichadetramitacao?idProposicao=2622855"
    },
    {
      "id": 2624035,
      "tipo": "PL",
      "numero": 2353,
      "ano": 2026,
      "ementa": "Estabelece obrigações às plataformas digitais de comunicação para detecção, remoção e notificação de conteúdos de maus-tratos a animais, e dá outras providências.",
      "data": "2026-05-12T19:22",
      "url": "https://www.camara.leg.br/proposicoesWeb/fichadetramitacao?idProposicao=2624035"
    }
  ],
  "discursos": [
    {
      "data": "2026-05-12T14:44",
      "fase": "Breves Comunicações",
      "tipo": "BREVES COMUNICAÇÕES",
      "resumo": "A SRA. ANA PAULA LIMA (Bloco/PT - SC. Sem revisão da oradora.) - Sr. Presidente, Sras. e Srs. Parlamentares, quero fazer um convite a todos os Parlamentares e a todos que estão nesta Casa para fazer u",
      "transcricao": "A SRA. ANA PAULA LIMA (Bloco/PT - SC. Sem revisão da oradora.) - Sr. Presidente, Sras. e Srs. Parlamentares, quero fazer um convite a todos os Parlamentares e a todos que estão nesta Casa para fazer uma visita no espaço Mário Covas, porque ali há uma exposição da Semana Brasileira de Enfermagem, que começa hoje, quando comemoramos o Dia do Enfermeiro, da Enfermeira, e vai até o dia 20 de maio, quando se comemora o Dia do Técnico e Auxiliar de Enfermagem. Falo isso porque, o dia de hoje, 12 de maio, Dia Internacional da Enfermagem, é um dia que também celebro, porque faço parte desta categoria. Sou enfermeira de profissão, e foi assim que tornei realidade algo que também me move através da política, nos meus mandatos, que é cuidar das pessoas. Quero, então, homenagear todos os enfermeiros e enfermeiras de todo o nosso País, os profissionais que sustentam a saúde, que são a espinha dorsal do Sistema Único de Saúde, e que, no dia 20 de maio, data que também homenageamos os auxiliares e técnicos, realizamos, então, a Semana da Enfermagem Brasileira deste ano com o tema \"Técnica, Ética e Política: Pilares Inegociáveis do Cuidado\". São mais de 3 milhões de profissionais da área da enfermagem, 70% de toda a força do trabalho em saúde, 61,9% dos vínculos com o Sistema Único de Saúde. Somos quem vacina, quem acolhe, quem acompanha para o parto, quem está na hora da dor, da assistência hospitalar, na prevenção da saúde, na prevenção de doenças. Estamos presentes na ciência, na academia e também na política. Somos quem está presente desde o primeiro dia de vida até o último dia de vida, inclusive consolando as pessoas na hora do luto. Não existe o Sistema Único de Saúde sem os profissionais de enfermagem, mas nada disso se sustenta sem ética. E a ética nos obriga a olhar para as condições em que este cuidado acontece. Uma categoria que é 87% feminina carrega sobre si a naturalização histórica do cuidar como atributo da mulher, o que inviabiliza a sobrecarga e também adoece. Precisamos falar da saúde mental de quem cuida de todos, mas muitas vezes não encontra cuidado para si. Por isso que nesta semana da enfermagem nós estamos lutando aqui por algo que já foi votado nesta Casa, que é o piso da enfermagem. E agora, estamos em uma luta maior para a aprovação da PEC 19, que se encontra no Senado Federal, que associa o Piso Nacional da Enfermagem juntamente com a carga horária de 36 horas semanais, que já está pronto para votar no Plenário do Senado Federal e categoria está se mobilizando para que isto aconteça o mais rápido possível. Minha fala hoje é para homenagear toda esta categoria tão importante para prevenir e manter a saúde da população brasileira. Parabéns a todos os profissionais de enfermagem! Presidente, solicito que o meu pronunciamento seja divulgado no programa A Voz do Brasil, por gentileza."
    },
    {
      "data": "2026-04-28T14:52",
      "fase": "Breves Comunicações",
      "tipo": "PELA ORDEM",
      "resumo": "A SRA. ANA PAULA LIMA (Bloco/PT - SC. Pela ordem. Sem revisão da oradora.) - Obrigada, Sr. Presidente. É uma grata satisfação receber neste plenário uma grande amiga, Heike Weege, que coordena o Núcle",
      "transcricao": "A SRA. ANA PAULA LIMA (Bloco/PT - SC. Pela ordem. Sem revisão da oradora.) - Obrigada, Sr. Presidente. É uma grata satisfação receber neste plenário uma grande amiga, Heike Weege, que coordena o Núcleo Setorial do Partido dos Trabalhadores Internacional, em Barcelona, na Espanha. Ela está neste momento visitando o o Parlamento Brasileiro, bem como também todos os familiares que ainda convivem aqui no Brasil. Dou as boas-vindas para a Heike, que com muita satisfação esteve presente, inclusive, no Congresso PT, que se realizou aqui em Brasília, no final de semana. Bem-vinda ao Parlamento Brasileiro."
    }
  ],
  "orgaos": [
    {
      "nome": "Comissão Especial para estudo das razões do aumento de denúncias de violência obstétrica e a alta taxa de morte materna no Brasil",
      "sigla": "CEOBSTET",
      "cargo": "2º Vice-Presidente",
      "desde": "2023-04-11T00:00"
    },
    {
      "nome": "Secretaria da Mulher",
      "sigla": "SEMULHER",
      "cargo": "Titular",
      "desde": "2023-05-04T00:00"
    },
    {
      "nome": "Comissão Externa destinada a elaborar propostas para analisar o enfrentamento da tuberculose como compromisso internacional para a eliminação desta doença como problema de saúde pública até o ano de 2030, conforme preconizado pela Organização das Nações Unidas (ONU)",
      "sigla": "CEXTUBER",
      "cargo": "Titular",
      "desde": "2023-09-05T00:00"
    },
    {
      "nome": "Comissão Especial destinada a estudar e analisar formas de prevenção e auxílio a desastres e calamidades naturais que vêm assolando o Território Nacional",
      "sigla": "CEDESNAT",
      "cargo": "Titular",
      "desde": "2024-02-07T00:00"
    },
    {
      "nome": "Comissão Especial para estudo das razões do aumento de denúncias de violência obstétrica e a alta taxa de morte materna no Brasil",
      "sigla": "CEOBSTET",
      "cargo": "Titular",
      "desde": "2024-02-07T00:00"
    },
    {
      "nome": "Comissão Especial destinada a proferir parecer ao Projeto de Lei nº 733, de 2025, do Sr. Leur Lomanto Júnior, que \"dispõe sobre o Sistema Portuário Brasileiro, regula a exploração dos portos, as atividades de operação portuária, o trabalho portuário e dá outras providências\"",
      "sigla": "PL073325",
      "cargo": "Titular",
      "desde": "2025-07-08T00:00"
    },
    {
      "nome": "Comissão de Saúde",
      "sigla": "CSAUDE",
      "cargo": "Titular",
      "desde": "2026-02-03T00:00"
    },
    {
      "nome": "Comissão de Previdência, Assistência Social, Infância, Adolescência e Família",
      "sigla": "CPASF",
      "cargo": "Suplente",
      "desde": "2026-02-04T00:00"
    },
    {
      "nome": "Comissão de Constituição e Justiça e de Cidadania",
      "sigla": "CCJC",
      "cargo": "Suplente",
      "desde": "2026-02-09T00:00"
    }
  ],
  "url_votacoes": "https://www.camara.leg.br/deputados/220556/votacoes-nominais-plenario/2026"
}