{
  "id": 220594,
  "nome": "Coronel Assis",
  "partido": "PL",
  "uf": "MT",
  "foto_url": "https://www.camara.leg.br/internet/deputado/bandep/220594.jpg",
  "score": 30.85,
  "rank": 101,
  "proposicoes": [],
  "discursos": [],
  "orgaos": [
    {
      "nome": "Comissão Externa destinada a acompanhar, in loco, o processo de intervenção na saúde pública do município de Cuiabá-MT, decretado pelo Tribunal de Justiça do estado de Mato Grosso",
      "sigla": "CEXSAUMT",
      "cargo": "Titular",
      "desde": "2023-03-31T00:00"
    },
    {
      "nome": "Bancada Negra da Câmara dos Deputados, criada pela Resolução n. 6, de 2023, que acresceu ao Regimento Interno da Câmara dos Deputados o Capítulo VI, do Título I, com os artigos 13-A e 13-B",
      "sigla": "BANEGRA",
      "cargo": "Titular",
      "desde": "2023-11-02T00:00"
    },
    {
      "nome": "Comissão Externa destinada a acompanhar as autoridades competentes na investigação e apuração da crise humanitária dos indígenas Yanomami, na região Norte do país",
      "sigla": "CEXYANOM",
      "cargo": "Titular",
      "desde": "2024-05-14T00:00"
    },
    {
      "nome": "Comissão Especial destinada a proferir parecer à Proposta de Emenda à Constituição n. 18, de 2025, do Poder Executivo, que \"altera os art. 21, art. 22, art. 23, art. 24 e art. 144 da Constituição, para dispor sobre competências da União, dos Estados, do Distrito Federal e dos Municípios relativas à segurança pública\"",
      "sigla": "PEC01825",
      "cargo": "Titular",
      "desde": "2025-09-09T00:00"
    },
    {
      "nome": "Comissão Especial destinada a proferir parecer ao Projeto de Lei nº 8085, de 2014, do Senado Federal, que \"altera a Lei nº 9.503, de 23 de setembro de 1997, que institui o Código de Trânsito Brasileiro, para instituir a obrigatoriedade da prática de direção veicular em vias públicas para fins de formação de condutores\"",
      "sigla": "PL808514",
      "cargo": "Suplente",
      "desde": "2026-02-27T00:00"
    },
    {
      "nome": "Comissão de Constituição e Justiça e de Cidadania",
      "sigla": "CCJC",
      "cargo": "Titular",
      "desde": "2026-04-23T00:00"
    },
    {
      "nome": "Comissão de Segurança Pública e Combate ao Crime Organizado",
      "sigla": "CSPCCO",
      "cargo": "Suplente",
      "desde": "2026-04-24T00:00"
    }
  ],
  "url_votacoes": "https://www.camara.leg.br/deputados/220594/votacoes-nominais-plenario/2026"
}