{
  "id": 220660,
  "nome": "Yury do Paredão",
  "partido": "MDB",
  "uf": "CE",
  "foto_url": "https://www.camara.leg.br/internet/deputado/bandep/220660.jpg",
  "score": 2.04,
  "rank": 511,
  "proposicoes": [],
  "discursos": [],
  "orgaos": [
    {
      "nome": "Bancada Negra da Câmara dos Deputados, criada pela Resolução n. 6, de 2023, que acresceu ao Regimento Interno da Câmara dos Deputados o Capítulo VI, do Título I, com os artigos 13-A e 13-B",
      "sigla": "BANEGRA",
      "cargo": "Titular",
      "desde": "2026-04-29T00:00"
    }
  ],
  "url_votacoes": "https://www.camara.leg.br/deputados/220660/votacoes-nominais-plenario/2026"
}