{
  "id": 220683,
  "nome": "Beto Richa",
  "partido": "PSDB",
  "uf": "PR",
  "foto_url": "https://www.camara.leg.br/internet/deputado/bandep/220683.jpg",
  "score": 28.51,
  "rank": 194,
  "proposicoes": [],
  "discursos": [],
  "orgaos": [
    {
      "nome": "Representação Brasileira no Parlamento do Mercosul",
      "sigla": "MERCOSUL",
      "cargo": "Titular",
      "desde": "2023-08-23T00:00"
    },
    {
      "nome": "Comissão Especial destinada a proferir parecer ao Projeto de Lei nº 733, de 2025, do Sr. Leur Lomanto Júnior, que \"dispõe sobre o Sistema Portuário Brasileiro, regula a exploração dos portos, as atividades de operação portuária, o trabalho portuário e dá outras providências\"",
      "sigla": "PL073325",
      "cargo": "Suplente",
      "desde": "2025-07-09T00:00"
    },
    {
      "nome": "Comissão de Indústria, Comércio e Serviços",
      "sigla": "CICS",
      "cargo": "1º Vice-Presidente",
      "desde": "2026-04-14T00:00"
    },
    {
      "nome": "Comissão de Indústria, Comércio e Serviços",
      "sigla": "CICS",
      "cargo": "Titular",
      "desde": "2026-04-14T00:00"
    }
  ],
  "url_votacoes": "https://www.camara.leg.br/deputados/220683/votacoes-nominais-plenario/2026"
}