{
  "id": 233592,
  "nome": "Paulo Lemos",
  "partido": "PT",
  "uf": "AP",
  "foto_url": "https://www.camara.leg.br/internet/deputado/bandep/233592.jpg",
  "score": 22.95,
  "rank": 294,
  "proposicoes": [
    {
      "id": 2637237,
      "tipo": "PL",
      "numero": 3479,
      "ano": 2026,
      "ementa": "Estabelece o marco legal do Registro Nacional de Beneficiários Finais, dispõe sobre a integração, atualização, verificação, interoperabilidade e acesso às informações relativas aos beneficiários finais de pessoas jurídicas e estruturas legais, e fortalece os mecanismos de prevenção à lavagem de dinheiro, corrupção, evasão fiscal, ocultação patrimonial e infiltração da criminaliza organizada na economia formal.",
      "data": "2026-07-06T13:23",
      "url": "https://www.camara.leg.br/proposicoesWeb/fichadetramitacao?idProposicao=2637237"
    }
  ],
  "discursos": [],
  "orgaos": [
    {
      "nome": "Bancada Negra da Câmara dos Deputados, criada pela Resolução n. 6, de 2023, que acresceu ao Regimento Interno da Câmara dos Deputados o Capítulo VI, do Título I, com os artigos 13-A e 13-B",
      "sigla": "BANEGRA",
      "cargo": "Titular",
      "desde": "2026-03-31T00:00"
    },
    {
      "nome": "Comissão de Administração e Serviço Público",
      "sigla": "CASP",
      "cargo": "Titular",
      "desde": "2026-04-17T00:00"
    },
    {
      "nome": "Comissão de Educação",
      "sigla": "CE",
      "cargo": "Titular",
      "desde": "2026-04-22T00:00"
    }
  ],
  "url_votacoes": "https://www.camara.leg.br/deputados/233592/votacoes-nominais-plenario/2026"
}